{
	"menuTitles": [
        {
			"title": "Charts",
			"icon": "chartsIcon",
			"link": "charts"
        },
        {
			"title": "Maps",
			"icon": "MapIcons",
			"link": "maps"
        }
    ],
    "subMenus": [
        {
            "activeMenu": "charts",
            "backIcon": "arrowIcon",
            "menuTitle": "Charts",
            "menuLinks": [
                {
                    "title": "Bar",
                    "icon": "barIcon",
                    "link": "/"
                },
                {
                    "title": "Scatter",
                    "icon": "scatterIcon",
                    "link": "/scatter"
                },
                {
                    "title": "Line",
                    "icon": "lineIcon",
                    "link": "/line"
                }
            ]
        },
        {
            "activeMenu": "maps",
            "backIcon": "arrowIcon",
            "menuTitle": "Maps",
            "menuLinks": [
                {
                    "title": "Globe",
                    "icon": "globeIcon",
                    "link": "/globe"
                }
            ]
        }
    ]
}